vonage_verify_v2/__init__.py
vonage_verify_v2/_version.py
vonage_verify_v2/enums.py
vonage_verify_v2/errors.py
vonage_verify_v2/requests.py
vonage_verify_v2/responses.py
vonage_verify_v2/verify_v2.py
vonage_verify_v2-1.1.3.dist-info/METADATA
vonage_verify_v2-1.1.3.dist-info/WHEEL
vonage_verify_v2-1.1.3.dist-info/top_level.txt
vonage_verify_v2-1.1.3.dist-info/RECORD
